<annotation><filename>20220225-175856.jpg</filename><folder>FFBDataset</folder><source><database>FFBDataset</database><annotation>custom</annotation><image>custom</image></source><size><width>1280</width><height>720</height><depth>3</depth></size><segmented>0</segmented><object><name>Bottle</name><pose>unspecified</pose><truncated>0</truncated><difficult>0</difficult><bndbox><xmin>539</xmin><ymin>361</ymin><xmax>685</xmax><ymax>681</ymax></bndbox></object><object><name>Bottle</name><pose>unspecified</pose><truncated>0</truncated><difficult>0</difficult><bndbox><xmin>450</xmin><ymin>16</ymin><xmax>617</xmax><ymax>381</ymax></bndbox></object></annotation>